{
    "Workouts": 
    [
        {
            "id": 3,
            "name": "The Insane Cardio HIIT",
            "type": "HIIT Workout",
            "summary": "This workout will help you lose that stubborn body fat! Follow this for three times a week for no more than 30 minutes- preferably in the morning before breakfast and lifting", 
            "plan":
            {
                "warmup":
                [
                    {
                        "exercisename": "Jog in place",
                        "sets": "1",
                        "reps": "30 seconds",
                        "rest": "10 second rest",
                        "example":"https://youtu.be/5Yz9odanXN4"  
                    },
                    {
                        "exercisename": "Overhead stretch + toe touch",
                        "sets": "1",
                        "reps": "30 seconds for each side",
                        "rest": "10 second rest",
                        "example":"https://youtu.be/5Yz9odanXN4" 
                    },
                    {
                        "exercisename": "Front Kicks",
                        "sets": "1",
                        "reps": "30 seconds",
                        "rest": "10 second rest",
                        "example":"https://youtu.be/5Yz9odanXN4" 
                    },
                    {
                        "exercisename": "Jumping Jacks",
                        "sets": "1",
                        "reps": "30 seconds",
                        "rest": "10 second rest",
                        "example":"https://youtu.be/5Yz9odanXN4" 
                    },
                    {
                        "exercisename": "Alternating Jumping Lunges in Place",
                        "sets": "1",
                        "reps": "As much as you can do in 30 seconds",
                        "rest": "10 second rest",
                        "example":"https://youtu.be/5Yz9odanXN4" 
                    }
                ],

                "mainset":
                [
                    {
                        "exercisename": "Sprints",
                        "sets": "2",
                        "reps": "As much as you can do in 30 seconds",
                        "rest": "10 second rest",
                        "example":"https://youtu.be/5Yz9odanXN4"
                    },
                    {
                        "exercisename": "Jumping Squats",
                        "sets": "2",
                        "reps": "As much as you can do in 30 seconds",
                        "rest": "20 second rest",
                        "example":"https://youtu.be/5Yz9odanXN4"
                    },
                    {
                        "exercisename": "Burpee",
                        "sets": "2",
                        "reps": "As much as you can do in 30 seconds",
                        "rest": "20 second rest",
                        "example":"https://youtu.be/5Yz9odanXN4"
                    },
                    {
                        "exercisename": "Bear Crawls",
                        "sets": "1",
                        "reps": "As much as you can do in 30 seconds",
                        "rest": "10 second rest",
                        "example":"https://youtu.be/5Yz9odanXN4"
                    },
                    {
                        "exercisename": "lunges with a twist",
                        "sets": "2",
                        "reps": "As much as you can do in 30 seconds",
                        "rest": "10 second rest",
                        "example":"https://youtu.be/5Yz9odanXN4"
                    },
                    {
                        "exercisename": "High Knees in Place",
                        "sets": "2",
                        "reps": "As much as you can do in 30 seconds",
                        "rest": "10 second rest",
                        "example":"https://youtu.be/5Yz9odanXN4"
                    },
                    {
                        "exercisename": "Alternating Jumping Lunges in Place",
                        "sets": "1",
                        "reps": "As much as you can do in 30 seconds",
                        "rest": "10 second rest",
                        "example":"https://youtu.be/5Yz9odanXN4"
                    }
                ]

            }
        }
    ]
}